rtl/core/alu.v
module alu (
    input [31:0] A, B,
    input [3:0] ALUControl,
    output reg [31:0] result,
    output zero
);
    parameter ADD = 4'd0;
    parameter SUB = 4'd1;

    parameter AND = 4'd2;
    parameter OR = 4'd3;
    parameter XOR = 4'd4;

    parameter SLT = 4'd5;

    
    always @(*) begin
        case (ALUControl)
            ADD: result = A + B;
            SUB: result = A - B;
            AND: result = A & B;
            OR: result = A | B;
            XOR: result = A ^ B;
            SLT: result = $signed(A) < $signed(B);
            default: result = 32'bx;
        endcase
    end

    assign zero = (result == 0);

endmodule

rtl/core/alu_control.v
module alu_control (
    input [1:0] ALUop,
    input [2:0] funct3, 
    input [6:0] funct7,
    output reg [3:0] ALUControl
);

    always @(*) begin
        
        case (ALUop)
            //load,store,addi -> ADD
            2'b00: ALUControl = 4'd0;      

            //branch -> SUB
            2'b01: ALUControl = 4'd1;      

            //All funct3-based ALU decoding
            2'b10:
                begin                   
                    case (funct3)
                        3'b000:    if (funct7 == 7'b0000000) ALUControl = 4'd0;            //Add
                                else if (funct7 == 7'b0100000) ALUControl = 4'd1;       //Sub
                                else ALUControl = 4'bx;

                        3'b111: ALUControl = 4'd2;            //And
                        3'b110: ALUControl = 4'd3;            //Or
                        3'b100: ALUControl = 4'd4;            //Xor
                        3'b010: ALUControl = 4'd5;            //SLT

                        default: ALUControl = 4'bx;
                    endcase
                end

            2'b11: ALUControl = 4'bx;

            default: ALUControl = 4'bx;
        endcase

    end
    
endmodule

tb/alu_tb.v
`timescale 1ns/1ps

module alu_tb;

    reg  [31:0] A, B;
    reg  [1:0]  ALUop;
    reg  [2:0]  funct3;
    reg  [6:0]  funct7;

    wire [3:0]  ALUControl;
    wire [31:0] result;
    wire        zero;

    // ALU Control
    alu_control u0 (
        .ALUop(ALUop),
        .funct3(funct3),
        .funct7(funct7),
        .ALUControl(ALUControl)
    );

    // ALU
    alu u1 (
        .A(A),
        .B(B),
        .ALUControl(ALUControl),
        .result(result),
        .zero(zero)
    );

    // Task for applying test vectors
    task run_test;

        input [1:0]  t_ALUop;
        input [2:0]  t_funct3;
        input [6:0]  t_funct7;
        input [31:0] t_A;
        input [31:0] t_B;

        begin

            ALUop  = t_ALUop;
            funct3 = t_funct3;
            funct7 = t_funct7;

            A = t_A;
            B = t_B;

            #10;

            $display("-------------------------------------------");
            $display("TIME = %0t", $time);
            $display("ALUop      = %b", ALUop);
            $display("funct3     = %b", funct3);
            $display("funct7     = %b", funct7);
            $display("A           = %0d", $signed(A));
            $display("B           = %0d", $signed(B));
            $display("ALUControl  = %b", ALUControl);
            $display("RESULT      = %0d", $signed(result));
            $display("ZERO        = %b", zero);

        end

    endtask


    initial begin

        // =========================
        // ADD
        // =========================
        run_test(
            2'b10,
            3'b000,
            7'b0000000,
            32'd10,
            32'd7
        );

        // =========================
        // SUB
        // =========================
        run_test(
            2'b10,
            3'b000,
            7'b0100000,
            32'd15,
            32'd9
        );

        // =========================
        // AND
        // =========================
        run_test(
            2'b10,
            3'b111,
            7'b0000000,
            32'b1100,
            32'b1010
        );

        // =========================
        // OR
        // =========================
        run_test(
            2'b10,
            3'b110,
            7'b0000000,
            32'b1100,
            32'b1010
        );

        // =========================
        // XOR
        // =========================
        run_test(
            2'b10,
            3'b100,
            7'b0000000,
            32'b1100,
            32'b1010
        );

        // =========================
        // SLT : 3 < 7
        // =========================
        run_test(
            2'b10,
            3'b010,
            7'b0000000,
            32'd3,
            32'd7
        );

        // =========================
        // SLT : 9 < 2
        // =========================
        run_test(
            2'b10,
            3'b010,
            7'b0000000,
            32'd9,
            32'd2
        );

        // =========================
        // SLT : -4 < 2
        // =========================
        run_test(
            2'b10,
            3'b010,
            7'b0000000,
            -32'd4,
            32'd2
        );

        // =========================
        // SLT : 2 < -4
        // =========================
        run_test(
            2'b10,
            3'b010,
            7'b0000000,
            32'd2,
            -32'd4
        );

        // =========================
        // ADDI path
        // ALUop = 00
        // =========================
        run_test(
            2'b00,
            3'b000,
            7'b0000000,
            32'd20,
            32'd5
        );

        // =========================
        // Branch path : equal
        // ALUop = 01
        // =========================
        run_test(
            2'b01,
            3'b000,
            7'b0000000,
            32'd8,
            32'd8
        );

        // =========================
        // Branch path : not equal
        // =========================
        run_test(
            2'b01,
            3'b000,
            7'b0000000,
            32'd8,
            32'd3
        );

        #20;
        $finish;

    end


    initial begin
        $dumpfile("sim/waveforms/alu.vcd");
        $dumpvars(0, alu_tb);
    end

endmodule

sim/waveforms/alu.vcd
$date
	Mon May 25 11:40:05 2026
$end
$version
	Icarus Verilog
$end
$timescale
	1ps
$end
$scope module alu_tb $end
$var wire 1 ! zero $end
$var wire 32 " result [31:0] $end
$var wire 4 # ALUControl [3:0] $end
$var reg 32 $ A [31:0] $end
$var reg 2 % ALUop [1:0] $end
$var reg 32 & B [31:0] $end
$var reg 3 ' funct3 [2:0] $end
$var reg 7 ( funct7 [6:0] $end
$scope module u0 $end
$var wire 2 ) ALUop [1:0] $end
$var wire 3 * funct3 [2:0] $end
$var wire 7 + funct7 [6:0] $end
$var reg 4 , ALUControl [3:0] $end
$upscope $end
$scope module u1 $end
$var wire 32 - A [31:0] $end
$var wire 4 . ALUControl [3:0] $end
$var wire 32 / B [31:0] $end
$var wire 1 ! zero $end
$var parameter 4 0 ADD $end
$var parameter 4 1 AND $end
$var parameter 4 2 OR $end
$var parameter 4 3 SLT $end
$var parameter 4 4 SUB $end
$var parameter 4 5 XOR $end
$var reg 32 6 result [31:0] $end
$upscope $end
$scope task run_test $end
$var reg 32 7 t_A [31:0] $end
$var reg 2 8 t_ALUop [1:0] $end
$var reg 32 9 t_B [31:0] $end
$var reg 3 : t_funct3 [2:0] $end
$var reg 7 ; t_funct7 [6:0] $end
$upscope $end
$upscope $end
$enddefinitions $end
$comment Show the parameter values. $end
$dumpall
b100 5
b1 4
b101 3
b11 2
b10 1
b0 0
$end
#0
$dumpvars
b0 ;
b0 :
b111 9
b10 8
b1010 7
b10001 6
b111 /
b0 .
b1010 -
b0 ,
b0 +
b0 *
b10 )
b0 (
b0 '
b111 &
b10 %
b1010 $
b0 #
b10001 "
0!
$end
#10000
b110 "
b110 6
b1 #
b1 ,
b1 .
b1001 &
b1001 /
b1111 $
b1111 -
b100000 (
b100000 +
b1001 9
b1111 7
b100000 ;
#20000
b1000 "
b1000 6
b10 #
b10 ,
b10 .
b1010 &
b1010 /
b1100 $
b1100 -
b0 (
b0 +
b111 '
b111 *
b1010 9
b1100 7
b0 ;
b111 :
#30000
b1110 "
b1110 6
b11 #
b11 ,
b11 .
b110 '
b110 *
b110 :
#40000
b110 "
b110 6
b100 #
b100 ,
b100 .
b100 '
b100 *
b100 :
#50000
b1 "
b1 6
b101 #
b101 ,
b101 .
b111 &
b111 /
b11 $
b11 -
b10 '
b10 *
b111 9
b11 7
b10 :
#60000
1!
b0 "
b0 6
b10 &
b10 /
b1001 $
b1001 -
b10 9
b1001 7
#70000
0!
b1 "
b1 6
b11111111111111111111111111111100 $
b11111111111111111111111111111100 -
b11111111111111111111111111111100 7
#80000
1!
b0 "
b0 6
b11111111111111111111111111111100 &
b11111111111111111111111111111100 /
b10 $
b10 -
b11111111111111111111111111111100 9
b10 7
#90000
0!
b11001 "
b11001 6
b0 #
b0 ,
b0 .
b101 &
b101 /
b10100 $
b10100 -
b0 '
b0 *
b0 %
b0 )
b101 9
b10100 7
b0 :
b0 8
#100000
1!
b0 "
b0 6
b1 #
b1 ,
b1 .
b1000 &
b1000 /
b1000 $
b1000 -
b1 %
b1 )
b1000 9
b1000 7
b1 8
#110000
0!
b101 "
b101 6
b11 &
b11 /
b11 9
